clean_copy/__init__.py
clean_copy/clean_copy.py
clean_copy/cli.py
clean_copy-0.1.2.dist-info/METADATA
clean_copy-0.1.2.dist-info/WHEEL
clean_copy-0.1.2.dist-info/entry_points.txt
clean_copy-0.1.2.dist-info/RECORD
