Metadata-Version: 2.1
Name: clean-copy
Version: 0.1.2
Summary: 
Author: Yulin Li
Author-email: liyulin@pku.edu.cn
Requires-Python: >=3.8,<4.0
Classifier: Programming Language :: Python :: 3
Classifier: Programming Language :: Python :: 3.8
Classifier: Programming Language :: Python :: 3.9
Classifier: Programming Language :: Python :: 3.10
Classifier: Programming Language :: Python :: 3.11
Requires-Dist: click (>=8.1.3,<9.0.0)
Requires-Dist: pathspec (>=0.11.1,<0.12.0)
